<?xml version="1.0" encoding="utf-8"?>
<clothing-items>
 <clothing>
  <id>
   955679243
  </id>
  <name>
   New Balance Gloves K-5026
  </name>
  <category>
   Gloves
  </category>
  <size>
   M
  </size>
  <color>
   Синий
  </color>
  <material>
   Вискоза
  </material>
  <price>
   458933
  </price>
  <rating>
   3.15
  </rating>
  <reviews>
   30057
  </reviews>
  <new>
   -
  </new>
  <exclusive>
   yes
  </exclusive>
  <sporty>
   no
  </sporty>
 </clothing>
 <clothing>
  <id>
   772302891
  </id>
  <name>
   Vans Hat K-8318
  </name>
  <category>
   Hat
  </category>
  <size>
   XL
  </size>
  <color>
   Синий
  </color>
  <material>
   Полиэстер
  </material>
  <price>
   595760
  </price>
  <rating>
   1.28
  </rating>
  <reviews>
   679669
  </reviews>
  <new>
   -
  </new>
  <sporty>
   yes
  </sporty>
 </clothing>
 <clothing>
  <id>
   703281945
  </id>
  <name>
   New Balance Gloves I-5983
  </name>
  <category>
   Gloves
  </category>
  <size>
   S
  </size>
  <color>
   Красный
  </color>
  <material>
   Лен
  </material>
  <price>
   880444
  </price>
  <rating>
   1.84
  </rating>
  <reviews>
   35705
  </reviews>
  <new>
   -
  </new>
  <sporty>
   yes
  </sporty>
 </clothing>
 <clothing>
  <id>
   771213885
  </id>
  <name>
   Brooks Gloves K-9727
  </name>
  <category>
   Gloves
  </category>
  <size>
   XXL
  </size>
  <color>
   Зеленый
  </color>
  <material>
   Нейлон
  </material>
  <price>
   982742
  </price>
  <rating>
   1.34
  </rating>
  <reviews>
   62435
  </reviews>
  <new>
   -
  </new>
  <exclusive>
   yes
  </exclusive>
  <sporty>
   no
  </sporty>
 </clothing>
 <clothing>
  <id>
   395910401
  </id>
  <name>
   Lacoste Skirt P-3619
  </name>
  <category>
   Skirt
  </category>
  <size>
   L
  </size>
  <color>
   Зеленый
  </color>
  <material>
   Кожа
  </material>
  <price>
   290986
  </price>
  <rating>
   4.21
  </rating>
  <reviews>
   56014
  </reviews>
  <exclusive>
   yes
  </exclusive>
  <sporty>
   no
  </sporty>
 </clothing>
 <clothing>
  <id>
   362657200
  </id>
  <name>
   Puma Belts U-5680
  </name>
  <category>
   Belts
  </category>
  <size>
   XXL
  </size>
  <color>
   Оранжевый
  </color>
  <material>
   Полиэстер
  </material>
  <price>
   623987
  </price>
  <rating>
   2.64
  </rating>
  <reviews>
   933296
  </reviews>
  <exclusive>
   yes
  </exclusive>
  <sporty>
   yes
  </sporty>
 </clothing>
 <clothing>
  <id>
   592656124
  </id>
  <name>
   Reebok Hat K-7349
  </name>
  <category>
   Hat
  </category>
  <size>
   L
  </size>
  <color>
   Синий
  </color>
  <material>
   Шерсть
  </material>
  <price>
   974636
  </price>
  <rating>
   4.62
  </rating>
  <reviews>
   530784
  </reviews>
  <new>
   +
  </new>
  <exclusive>
   no
  </exclusive>
  <sporty>
   no
  </sporty>
 </clothing>
 <clothing>
  <id>
   613172851
  </id>
  <name>
   Fila Shirt T-9476
  </name>
  <category>
   Shirt
  </category>
  <size>
   S
  </size>
  <color>
   Красный
  </color>
  <material>
   Шерсть
  </material>
  <price>
   897163
  </price>
  <rating>
   1.67
  </rating>
  <reviews>
   438235
  </reviews>
  <new>
   -
  </new>
  <exclusive>
   yes
  </exclusive>
  <sporty>
   yes
  </sporty>
 </clothing>
 <clothing>
  <id>
   794611427
  </id>
  <name>
   DC Sweater S-9570
  </name>
  <category>
   Sweater
  </category>
  <size>
   S
  </size>
  <color>
   Фиолетовый
  </color>
  <material>
   Вискоза
  </material>
  <price>
   958092
  </price>
  <rating>
   1.8
  </rating>
  <reviews>
   685126
  </reviews>
  <exclusive>
   no
  </exclusive>
 </clothing>
 <clothing>
  <id>
   400835432
  </id>
  <name>
   Vans Shoes Z-2797
  </name>
  <category>
   Shoes
  </category>
  <size>
   S
  </size>
  <color>
   Желтый
  </color>
  <material>
   Хлопок
  </material>
  <price>
   745322
  </price>
  <rating>
   4.11
  </rating>
  <reviews>
   788810
  </reviews>
  <new>
   -
  </new>
  <exclusive>
   no
  </exclusive>
 </clothing>
 <clothing>
  <id>
   949275849
  </id>
  <name>
   Addidas Gloves X-9854
  </name>
  <category>
   Gloves
  </category>
  <size>
   M
  </size>
  <color>
   Оранжевый
  </color>
  <material>
   Нейлон
  </material>
  <price>
   289899
  </price>
  <rating>
   2.11
  </rating>
  <reviews>
   781057
  </reviews>
  <new>
   -
  </new>
  <sporty>
   yes
  </sporty>
 </clothing>
 <clothing>
  <id>
   988581186
  </id>
  <name>
   Converse Blouse J-4841
  </name>
  <category>
   Blouse
  </category>
  <size>
   S
  </size>
  <color>
   Желтый
  </color>
  <material>
   Шерсть
  </material>
  <price>
   684946
  </price>
  <rating>
   1.45
  </rating>
  <reviews>
   195492
  </reviews>
  <new>
   +
  </new>
  <exclusive>
   yes
  </exclusive>
  <sporty>
   no
  </sporty>
 </clothing>
 <clothing>
  <id>
   924692432
  </id>
  <name>
   Ellesse Shoes Q-9133
  </name>
  <category>
   Shoes
  </category>
  <size>
   M
  </size>
  <color>
   Фиолетовый
  </color>
  <material>
   Нейлон
  </material>
  <price>
   548685
  </price>
  <rating>
   3.22
  </rating>
  <reviews>
   583523
  </reviews>
  <new>
   -
  </new>
 </clothing>
 <clothing>
  <id>
   469678071
  </id>
  <name>
   Puma Gloves O-2918
  </name>
  <category>
   Gloves
  </category>
  <size>
   S
  </size>
  <color>
   Оранжевый
  </color>
  <material>
   Кожа
  </material>
  <price>
   368290
  </price>
  <rating>
   4.73
  </rating>
  <reviews>
   473062
  </reviews>
  <new>
   -
  </new>
  <exclusive>
   yes
  </exclusive>
 </clothing>
 <clothing>
  <id>
   943202280
  </id>
  <name>
   Converse Jeans U-9901
  </name>
  <category>
   Jeans
  </category>
  <size>
   S
  </size>
  <color>
   Голубой
  </color>
  <material>
   Шерсть
  </material>
  <price>
   785631
  </price>
  <rating>
   2.06
  </rating>
  <reviews>
   677122
  </reviews>
  <sporty>
   yes
  </sporty>
 </clothing>
 <clothing>
  <id>
   530467144
  </id>
  <name>
   Asics Hat E-5988
  </name>
  <category>
   Hat
  </category>
  <size>
   XXL
  </size>
  <color>
   Голубой
  </color>
  <material>
   Лен
  </material>
  <price>
   969869
  </price>
  <rating>
   1.15
  </rating>
  <reviews>
   139587
  </reviews>
  <sporty>
   no
  </sporty>
 </clothing>
 <clothing>
  <id>
   261770478
  </id>
  <name>
   Brooks Shirt B-7319
  </name>
  <category>
   Shirt
  </category>
  <size>
   L
  </size>
  <color>
   Оранжевый
  </color>
  <material>
   Шерсть
  </material>
  <price>
   516845
  </price>
  <rating>
   2.53
  </rating>
  <reviews>
   384670
  </reviews>
  <exclusive>
   yes
  </exclusive>
  <sporty>
   no
  </sporty>
 </clothing>
 <clothing>
  <id>
   432184028
  </id>
  <name>
   Ellesse Shirt F-4411
  </name>
  <category>
   Shirt
  </category>
  <size>
   S
  </size>
  <color>
   Оранжевый
  </color>
  <material>
   Вискоза
  </material>
  <price>
   655512
  </price>
  <rating>
   4.02
  </rating>
  <reviews>
   848935
  </reviews>
  <new>
   -
  </new>
  <exclusive>
   yes
  </exclusive>
  <sporty>
   no
  </sporty>
 </clothing>
 <clothing>
  <id>
   658221066
  </id>
  <name>
   Under Armour Socks J-8626
  </name>
  <category>
   Socks
  </category>
  <size>
   S
  </size>
  <color>
   Фиолетовый
  </color>
  <material>
   Полиэстер
  </material>
  <price>
   677073
  </price>
  <rating>
   3.74
  </rating>
  <reviews>
   570785
  </reviews>
  <sporty>
   yes
  </sporty>
 </clothing>
 <clothing>
  <id>
   345092931
  </id>
  <name>
   Reebok Socks P-5628
  </name>
  <category>
   Socks
  </category>
  <size>
   S
  </size>
  <color>
   Оранжевый
  </color>
  <material>
   Вискоза
  </material>
  <price>
   923953
  </price>
  <rating>
   2.33
  </rating>
  <reviews>
   288926
  </reviews>
  <new>
   -
  </new>
  <exclusive>
   no
  </exclusive>
  <sporty>
   yes
  </sporty>
 </clothing>
 <clothing>
  <id>
   449180566
  </id>
  <name>
   Vans Skirt M-2667
  </name>
  <category>
   Skirt
  </category>
  <size>
   XL
  </size>
  <color>
   Фиолетовый
  </color>
  <material>
   Хлопок
  </material>
  <price>
   787048
  </price>
  <rating>
   3.03
  </rating>
  <reviews>
   834277
  </reviews>
  <exclusive>
   no
  </exclusive>
  <sporty>
   no
  </sporty>
 </clothing>
 <clothing>
  <id>
   861218803
  </id>
  <name>
   Fila Jacket H-8824
  </name>
  <category>
   Jacket
  </category>
  <size>
   L
  </size>
  <color>
   Оранжевый
  </color>
  <material>
   Хлопок
  </material>
  <price>
   506985
  </price>
  <rating>
   2.65
  </rating>
  <reviews>
   924811
  </reviews>
  <sporty>
   yes
  </sporty>
 </clothing>
 <clothing>
  <id>
   462179154
  </id>
  <name>
   Lacoste Skirt V-5310
  </name>
  <category>
   Skirt
  </category>
  <size>
   XL
  </size>
  <color>
   Красный
  </color>
  <material>
   Вискоза
  </material>
  <price>
   401382
  </price>
  <rating>
   1.06
  </rating>
  <reviews>
   779196
  </reviews>
  <new>
   -
  </new>
  <sporty>
   no
  </sporty>
 </clothing>
 <clothing>
  <id>
   877714327
  </id>
  <name>
   Ellesse Shirt D-8864
  </name>
  <category>
   Shirt
  </category>
  <size>
   XL
  </size>
  <color>
   Оранжевый
  </color>
  <material>
   Нейлон
  </material>
  <price>
   130733
  </price>
  <rating>
   1.41
  </rating>
  <reviews>
   968388
  </reviews>
  <exclusive>
   no
  </exclusive>
 </clothing>
 <clothing>
  <id>
   760655762
  </id>
  <name>
   Lacoste Sweater Q-5155
  </name>
  <category>
   Sweater
  </category>
  <size>
   S
  </size>
  <color>
   Оранжевый
  </color>
  <material>
   Лен
  </material>
  <price>
   130577
  </price>
  <rating>
   3.29
  </rating>
  <reviews>
   751601
  </reviews>
 </clothing>
 <clothing>
  <id>
   130825092
  </id>
  <name>
   Reebok Sweater S-8182
  </name>
  <category>
   Sweater
  </category>
  <size>
   XXL
  </size>
  <color>
   Голубой
  </color>
  <material>
   Лен
  </material>
  <price>
   711199
  </price>
  <rating>
   1.21
  </rating>
  <reviews>
   998911
  </reviews>
  <exclusive>
   yes
  </exclusive>
  <sporty>
   no
  </sporty>
 </clothing>
 <clothing>
  <id>
   529369184
  </id>
  <name>
   Vans Blouse O-5892
  </name>
  <category>
   Blouse
  </category>
  <size>
   XL
  </size>
  <color>
   Оранжевый
  </color>
  <material>
   Полиэстер
  </material>
  <price>
   500810
  </price>
  <rating>
   4.32
  </rating>
  <reviews>
   646101
  </reviews>
  <new>
   -
  </new>
  <exclusive>
   no
  </exclusive>
  <sporty>
   no
  </sporty>
 </clothing>
 <clothing>
  <id>
   144513787
  </id>
  <name>
   Addidas Sweater R-4312
  </name>
  <category>
   Sweater
  </category>
  <size>
   XL
  </size>
  <color>
   Оранжевый
  </color>
  <material>
   Шерсть
  </material>
  <price>
   592901
  </price>
  <rating>
   3.73
  </rating>
  <reviews>
   666415
  </reviews>
  <new>
   -
  </new>
  <exclusive>
   no
  </exclusive>
  <sporty>
   yes
  </sporty>
 </clothing>
 <clothing>
  <id>
   947071120
  </id>
  <name>
   Asics T-shirt G-8389
  </name>
  <category>
   T-shirt
  </category>
  <size>
   S
  </size>
  <color>
   Желтый
  </color>
  <material>
   Нейлон
  </material>
  <price>
   616228
  </price>
  <rating>
   4.68
  </rating>
  <reviews>
   755350
  </reviews>
  <new>
   -
  </new>
  <sporty>
   no
  </sporty>
 </clothing>
 <clothing>
  <id>
   462456502
  </id>
  <name>
   DC Jacket C-1688
  </name>
  <category>
   Jacket
  </category>
  <size>
   S
  </size>
  <color>
   Синий
  </color>
  <material>
   Вискоза
  </material>
  <price>
   254090
  </price>
  <rating>
   1.72
  </rating>
  <reviews>
   570836
  </reviews>
  <new>
   +
  </new>
  <exclusive>
   no
  </exclusive>
  <sporty>
   no
  </sporty>
 </clothing>
 <clothing>
  <id>
   405805227
  </id>
  <name>
   New Balance Skirt U-1025
  </name>
  <category>
   Skirt
  </category>
  <size>
   XL
  </size>
  <color>
   Синий
  </color>
  <material>
   Полиэстер
  </material>
  <price>
   384935
  </price>
  <rating>
   4.83
  </rating>
  <reviews>
   701673
  </reviews>
  <exclusive>
   no
  </exclusive>
 </clothing>
 <clothing>
  <id>
   109362336
  </id>
  <name>
   Converse Socks P-6497
  </name>
  <category>
   Socks
  </category>
  <size>
   L
  </size>
  <color>
   Красный
  </color>
  <material>
   Лен
  </material>
  <price>
   317954
  </price>
  <rating>
   1.64
  </rating>
  <reviews>
   886911
  </reviews>
  <exclusive>
   yes
  </exclusive>
 </clothing>
 <clothing>
  <id>
   136539733
  </id>
  <name>
   Puma Pants B-3727
  </name>
  <category>
   Pants
  </category>
  <size>
   M
  </size>
  <color>
   Синий
  </color>
  <material>
   Полиэстер
  </material>
  <price>
   640312
  </price>
  <rating>
   3.04
  </rating>
  <reviews>
   666657
  </reviews>
  <sporty>
   no
  </sporty>
 </clothing>
 <clothing>
  <id>
   963873817
  </id>
  <name>
   Nike Skirt X-2376
  </name>
  <category>
   Skirt
  </category>
  <size>
   XL
  </size>
  <color>
   Зеленый
  </color>
  <material>
   Лен
  </material>
  <price>
   851351
  </price>
  <rating>
   3.41
  </rating>
  <reviews>
   409854
  </reviews>
 </clothing>
</clothing-items>
