<?xml version="1.0" encoding="utf-8"?>
<clothing-items>
 <clothing>
  <id>
   464771114
  </id>
  <name>
   Nike Socks O-6899
  </name>
  <category>
   Socks
  </category>
  <size>
   L
  </size>
  <color>
   Желтый
  </color>
  <material>
   Кожа
  </material>
  <price>
   848801
  </price>
  <rating>
   1.94
  </rating>
  <reviews>
   160430
  </reviews>
  <new>
   -
  </new>
  <sporty>
   yes
  </sporty>
 </clothing>
 <clothing>
  <id>
   966016009
  </id>
  <name>
   New Balance Jeans D-7243
  </name>
  <category>
   Jeans
  </category>
  <size>
   XL
  </size>
  <color>
   Зеленый
  </color>
  <material>
   Нейлон
  </material>
  <price>
   315915
  </price>
  <rating>
   3.27
  </rating>
  <reviews>
   656927
  </reviews>
  <new>
   -
  </new>
  <exclusive>
   no
  </exclusive>
 </clothing>
 <clothing>
  <id>
   884854060
  </id>
  <name>
   Puma Belts R-1290
  </name>
  <category>
   Belts
  </category>
  <size>
   XL
  </size>
  <color>
   Синий
  </color>
  <material>
   Шерсть
  </material>
  <price>
   524404
  </price>
  <rating>
   3.45
  </rating>
  <reviews>
   89268
  </reviews>
  <new>
   +
  </new>
  <exclusive>
   no
  </exclusive>
 </clothing>
 <clothing>
  <id>
   630426056
  </id>
  <name>
   DC Shirt R-3885
  </name>
  <category>
   Shirt
  </category>
  <size>
   M
  </size>
  <color>
   Оранжевый
  </color>
  <material>
   Лен
  </material>
  <price>
   772495
  </price>
  <rating>
   4.68
  </rating>
  <reviews>
   346494
  </reviews>
  <sporty>
   yes
  </sporty>
 </clothing>
 <clothing>
  <id>
   655365169
  </id>
  <name>
   Adidas Shirt L-3198
  </name>
  <category>
   Shirt
  </category>
  <size>
   L
  </size>
  <color>
   Желтый
  </color>
  <material>
   Полиэстер
  </material>
  <price>
   534823
  </price>
  <rating>
   1.5
  </rating>
  <reviews>
   741010
  </reviews>
  <new>
   -
  </new>
  <exclusive>
   no
  </exclusive>
 </clothing>
 <clothing>
  <id>
   185822739
  </id>
  <name>
   Asics Gloves C-3253
  </name>
  <category>
   Gloves
  </category>
  <size>
   XL
  </size>
  <color>
   Фиолетовый
  </color>
  <material>
   Шелк
  </material>
  <price>
   521148
  </price>
  <rating>
   1.99
  </rating>
  <reviews>
   976087
  </reviews>
  <new>
   +
  </new>
  <exclusive>
   no
  </exclusive>
  <sporty>
   no
  </sporty>
 </clothing>
 <clothing>
  <id>
   376636158
  </id>
  <name>
   Ellesse Umbrellas T-7650
  </name>
  <category>
   Umbrellas
  </category>
  <size>
   XXL
  </size>
  <color>
   Красный
  </color>
  <material>
   Кожа
  </material>
  <price>
   439034
  </price>
  <rating>
   3.54
  </rating>
  <reviews>
   794345
  </reviews>
  <new>
   -
  </new>
  <sporty>
   yes
  </sporty>
 </clothing>
 <clothing>
  <id>
   350223345
  </id>
  <name>
   Converse Handbags N-7234
  </name>
  <category>
   Handbags
  </category>
  <size>
   L
  </size>
  <color>
   Желтый
  </color>
  <material>
   Кожа
  </material>
  <price>
   326683
  </price>
  <rating>
   3.87
  </rating>
  <reviews>
   773619
  </reviews>
  <new>
   -
  </new>
 </clothing>
 <clothing>
  <id>
   837386440
  </id>
  <name>
   Lacoste Shirt N-6157
  </name>
  <category>
   Shirt
  </category>
  <size>
   S
  </size>
  <color>
   Голубой
  </color>
  <material>
   Кожа
  </material>
  <price>
   919074
  </price>
  <rating>
   2.43
  </rating>
  <reviews>
   387972
  </reviews>
  <new>
   +
  </new>
  <exclusive>
   yes
  </exclusive>
 </clothing>
 <clothing>
  <id>
   364674976
  </id>
  <name>
   Nike Socks L-3036
  </name>
  <category>
   Socks
  </category>
  <size>
   S
  </size>
  <color>
   Красный
  </color>
  <material>
   Кожа
  </material>
  <price>
   674402
  </price>
  <rating>
   2.33
  </rating>
  <reviews>
   619740
  </reviews>
  <new>
   -
  </new>
  <exclusive>
   yes
  </exclusive>
  <sporty>
   no
  </sporty>
 </clothing>
</clothing-items>
