<?xml version="1.0" encoding="utf-8"?>
<clothing-items>
 <clothing>
  <id>
   470772529
  </id>
  <name>
   PleinSport Belts Y-1776
  </name>
  <category>
   Belts
  </category>
  <size>
   XXL
  </size>
  <color>
   Зеленый
  </color>
  <material>
   Вискоза
  </material>
  <price>
   795530
  </price>
  <rating>
   1.23
  </rating>
  <reviews>
   189335
  </reviews>
  <new>
   -
  </new>
  <exclusive>
   no
  </exclusive>
 </clothing>
 <clothing>
  <id>
   153105335
  </id>
  <name>
   Converse Sweater F-5200
  </name>
  <category>
   Sweater
  </category>
  <size>
   XXL
  </size>
  <color>
   Красный
  </color>
  <material>
   Нейлон
  </material>
  <price>
   770291
  </price>
  <rating>
   2.44
  </rating>
  <reviews>
   725505
  </reviews>
  <new>
   -
  </new>
  <exclusive>
   no
  </exclusive>
  <sporty>
   no
  </sporty>
 </clothing>
 <clothing>
  <id>
   408381458
  </id>
  <name>
   DC Pants B-4706
  </name>
  <category>
   Pants
  </category>
  <size>
   XXL
  </size>
  <color>
   Красный
  </color>
  <material>
   Шелк
  </material>
  <price>
   222364
  </price>
  <rating>
   3.42
  </rating>
  <reviews>
   765852
  </reviews>
  <new>
   -
  </new>
  <exclusive>
   no
  </exclusive>
 </clothing>
 <clothing>
  <id>
   597656626
  </id>
  <name>
   Brooks Sweater N-6911
  </name>
  <category>
   Sweater
  </category>
  <size>
   L
  </size>
  <color>
   Оранжевый
  </color>
  <material>
   Вискоза
  </material>
  <price>
   826366
  </price>
  <rating>
   2.13
  </rating>
  <reviews>
   516012
  </reviews>
  <new>
   +
  </new>
 </clothing>
 <clothing>
  <id>
   376822298
  </id>
  <name>
   Puma Pants K-3679
  </name>
  <category>
   Pants
  </category>
  <size>
   XL
  </size>
  <color>
   Фиолетовый
  </color>
  <material>
   Кожа
  </material>
  <price>
   625623
  </price>
  <rating>
   4.98
  </rating>
  <reviews>
   485742
  </reviews>
  <sporty>
   yes
  </sporty>
 </clothing>
 <clothing>
  <id>
   254861569
  </id>
  <name>
   Puma T-shirt D-7224
  </name>
  <category>
   T-shirt
  </category>
  <size>
   XL
  </size>
  <color>
   Фиолетовый
  </color>
  <material>
   Нейлон
  </material>
  <price>
   827428
  </price>
  <rating>
   2.56
  </rating>
  <reviews>
   55683
  </reviews>
  <new>
   -
  </new>
  <exclusive>
   yes
  </exclusive>
  <sporty>
   yes
  </sporty>
 </clothing>
 <clothing>
  <id>
   860265388
  </id>
  <name>
   PleinSport Belts B-1429
  </name>
  <category>
   Belts
  </category>
  <size>
   XXL
  </size>
  <color>
   Желтый
  </color>
  <material>
   Кожа
  </material>
  <price>
   566021
  </price>
  <rating>
   3.72
  </rating>
  <reviews>
   866192
  </reviews>
  <new>
   -
  </new>
  <exclusive>
   no
  </exclusive>
 </clothing>
 <clothing>
  <id>
   713082728
  </id>
  <name>
   PleinSport T-shirt S-6695
  </name>
  <category>
   T-shirt
  </category>
  <size>
   S
  </size>
  <color>
   Красный
  </color>
  <material>
   Полиэстер
  </material>
  <price>
   738233
  </price>
  <rating>
   2.3
  </rating>
  <reviews>
   724185
  </reviews>
  <new>
   -
  </new>
  <exclusive>
   yes
  </exclusive>
  <sporty>
   no
  </sporty>
 </clothing>
 <clothing>
  <id>
   882713548
  </id>
  <name>
   Asics Umbrellas E-8206
  </name>
  <category>
   Umbrellas
  </category>
  <size>
   XXL
  </size>
  <color>
   Фиолетовый
  </color>
  <material>
   Лен
  </material>
  <price>
   254358
  </price>
  <rating>
   3.25
  </rating>
  <reviews>
   774042
  </reviews>
  <exclusive>
   no
  </exclusive>
  <sporty>
   yes
  </sporty>
 </clothing>
 <clothing>
  <id>
   857984270
  </id>
  <name>
   Brooks Socks B-7719
  </name>
  <category>
   Socks
  </category>
  <size>
   M
  </size>
  <color>
   Желтый
  </color>
  <material>
   Шелк
  </material>
  <price>
   500596
  </price>
  <rating>
   3.16
  </rating>
  <reviews>
   861671
  </reviews>
  <new>
   -
  </new>
 </clothing>
 <clothing>
  <id>
   983117108
  </id>
  <name>
   Addidas Gloves K-5234
  </name>
  <category>
   Gloves
  </category>
  <size>
   L
  </size>
  <color>
   Голубой
  </color>
  <material>
   Шерсть
  </material>
  <price>
   117450
  </price>
  <rating>
   2.94
  </rating>
  <reviews>
   711114
  </reviews>
  <exclusive>
   no
  </exclusive>
  <sporty>
   yes
  </sporty>
 </clothing>
 <clothing>
  <id>
   338751949
  </id>
  <name>
   Reebok Belts V-4758
  </name>
  <category>
   Belts
  </category>
  <size>
   L
  </size>
  <color>
   Красный
  </color>
  <material>
   Шелк
  </material>
  <price>
   210426
  </price>
  <rating>
   4.35
  </rating>
  <reviews>
   535926
  </reviews>
  <exclusive>
   yes
  </exclusive>
 </clothing>
 <clothing>
  <id>
   632563570
  </id>
  <name>
   DC Socks S-7743
  </name>
  <category>
   Socks
  </category>
  <size>
   XL
  </size>
  <color>
   Фиолетовый
  </color>
  <material>
   Нейлон
  </material>
  <price>
   579885
  </price>
  <rating>
   1.33
  </rating>
  <reviews>
   206483
  </reviews>
  <exclusive>
   no
  </exclusive>
  <sporty>
   no
  </sporty>
 </clothing>
 <clothing>
  <id>
   912997111
  </id>
  <name>
   Fila Socks T-8582
  </name>
  <category>
   Socks
  </category>
  <size>
   L
  </size>
  <color>
   Голубой
  </color>
  <material>
   Полиэстер
  </material>
  <price>
   318091
  </price>
  <rating>
   4.92
  </rating>
  <reviews>
   854798
  </reviews>
  <new>
   -
  </new>
  <exclusive>
   yes
  </exclusive>
  <sporty>
   yes
  </sporty>
 </clothing>
 <clothing>
  <id>
   981490296
  </id>
  <name>
   Vans Hat U-5203
  </name>
  <category>
   Hat
  </category>
  <size>
   M
  </size>
  <color>
   Красный
  </color>
  <material>
   Хлопок
  </material>
  <price>
   282865
  </price>
  <rating>
   3.98
  </rating>
  <reviews>
   688889
  </reviews>
  <new>
   -
  </new>
  <exclusive>
   no
  </exclusive>
  <sporty>
   yes
  </sporty>
 </clothing>
 <clothing>
  <id>
   863978392
  </id>
  <name>
   Ellesse Jeans G-3851
  </name>
  <category>
   Jeans
  </category>
  <size>
   S
  </size>
  <color>
   Фиолетовый
  </color>
  <material>
   Нейлон
  </material>
  <price>
   752156
  </price>
  <rating>
   2.2
  </rating>
  <reviews>
   512331
  </reviews>
  <exclusive>
   yes
  </exclusive>
  <sporty>
   no
  </sporty>
 </clothing>
 <clothing>
  <id>
   855835395
  </id>
  <name>
   Adidas Umbrellas N-1009
  </name>
  <category>
   Umbrellas
  </category>
  <size>
   XL
  </size>
  <color>
   Желтый
  </color>
  <material>
   Хлопок
  </material>
  <price>
   860933
  </price>
  <rating>
   1.86
  </rating>
  <reviews>
   890177
  </reviews>
  <new>
   -
  </new>
  <exclusive>
   yes
  </exclusive>
  <sporty>
   no
  </sporty>
 </clothing>
 <clothing>
  <id>
   142131018
  </id>
  <name>
   Vans Skirt A-6679
  </name>
  <category>
   Skirt
  </category>
  <size>
   M
  </size>
  <color>
   Желтый
  </color>
  <material>
   Шелк
  </material>
  <price>
   693530
  </price>
  <rating>
   1.09
  </rating>
  <reviews>
   671023
  </reviews>
  <new>
   -
  </new>
  <sporty>
   no
  </sporty>
 </clothing>
 <clothing>
  <id>
   564910728
  </id>
  <name>
   PleinSport Blouse F-7893
  </name>
  <category>
   Blouse
  </category>
  <size>
   XL
  </size>
  <color>
   Красный
  </color>
  <material>
   Хлопок
  </material>
  <price>
   868204
  </price>
  <rating>
   4.8
  </rating>
  <reviews>
   256007
  </reviews>
 </clothing>
 <clothing>
  <id>
   738417947
  </id>
  <name>
   New Balance Sweater A-4030
  </name>
  <category>
   Sweater
  </category>
  <size>
   XL
  </size>
  <color>
   Синий
  </color>
  <material>
   Кожа
  </material>
  <price>
   679247
  </price>
  <rating>
   2.18
  </rating>
  <reviews>
   32365
  </reviews>
  <sporty>
   no
  </sporty>
 </clothing>
 <clothing>
  <id>
   685808723
  </id>
  <name>
   Adidas Blouse X-5717
  </name>
  <category>
   Blouse
  </category>
  <size>
   M
  </size>
  <color>
   Оранжевый
  </color>
  <material>
   Кожа
  </material>
  <price>
   554269
  </price>
  <rating>
   4.93
  </rating>
  <reviews>
   802531
  </reviews>
  <exclusive>
   no
  </exclusive>
 </clothing>
</clothing-items>
